RsCmwGprfGen/RsCmwGprfGen.py
RsCmwGprfGen/__init__.py
RsCmwGprfGen/enums.py
RsCmwGprfGen/repcap.py
RsCmwGprfGen/CustomFiles/__init__.py
RsCmwGprfGen/CustomFiles/events.py
RsCmwGprfGen/CustomFiles/reliability.py
RsCmwGprfGen/CustomFiles/utilities.py
RsCmwGprfGen/Implementations/__init__.py
RsCmwGprfGen/Implementations/Configure/__init__.py
RsCmwGprfGen/Implementations/Configure/SingleCmw/__init__.py
RsCmwGprfGen/Implementations/Configure/SingleCmw/Usage/__init__.py
RsCmwGprfGen/Implementations/Configure/SingleCmw/Usage/Tx/All.py
RsCmwGprfGen/Implementations/Configure/SingleCmw/Usage/Tx/__init__.py
RsCmwGprfGen/Implementations/Configure/Spath/__init__.py
RsCmwGprfGen/Implementations/Configure/Spath/Usage/Bench.py
RsCmwGprfGen/Implementations/Configure/Spath/Usage/__init__.py
RsCmwGprfGen/Implementations/Route/__init__.py
RsCmwGprfGen/Implementations/Route/Scenario/IqOut.py
RsCmwGprfGen/Implementations/Route/Scenario/Salone.py
RsCmwGprfGen/Implementations/Route/Scenario/__init__.py
RsCmwGprfGen/Implementations/Source/IqSettings.py
RsCmwGprfGen/Implementations/Source/RfSettings.py
RsCmwGprfGen/Implementations/Source/__init__.py
RsCmwGprfGen/Implementations/Source/Arb/File.py
RsCmwGprfGen/Implementations/Source/Arb/Msegment.py
RsCmwGprfGen/Implementations/Source/Arb/Segments.py
RsCmwGprfGen/Implementations/Source/Arb/__init__.py
RsCmwGprfGen/Implementations/Source/Arb/Marker/Delays.py
RsCmwGprfGen/Implementations/Source/Arb/Marker/__init__.py
RsCmwGprfGen/Implementations/Source/Arb/Samples/Range.py
RsCmwGprfGen/Implementations/Source/Arb/Samples/__init__.py
RsCmwGprfGen/Implementations/Source/Arb/UdMarker/Clist.py
RsCmwGprfGen/Implementations/Source/Arb/UdMarker/__init__.py
RsCmwGprfGen/Implementations/Source/Dtone/Level.py
RsCmwGprfGen/Implementations/Source/Dtone/Ofrequency.py
RsCmwGprfGen/Implementations/Source/Dtone/__init__.py
RsCmwGprfGen/Implementations/Source/ListPy/Dgain.py
RsCmwGprfGen/Implementations/Source/ListPy/Dtime.py
RsCmwGprfGen-4.0.140.dist-info/METADATA
RsCmwGprfGen-4.0.140.dist-info/WHEEL
RsCmwGprfGen-4.0.140.dist-info/top_level.txt
RsCmwGprfGen-4.0.140.dist-info/RECORD
